{"name":"Tool 2 - Verificar materiales con stock suficiente","id":"hu-19-mcp-de-gestion-de-productos;tool-2---verificar-materiales-con-stock-suficiente","scenarioId":"mcp-productos:Tool 2 - Verificar materiales con stock suficiente","methodName":"Tool 2 - Verificar materiales con stock suficiente","testSteps":[{"number":1,"description":"Given el MCP de productos esta disponible y conectado a la base de datos","duration":0,"startTime":"2026-05-16T23:46:59.540206547-05:00[America/Bogota]","result":"SUCCESS","reportData":[{"title":"MCP conectado a la BD","path":"downloadable/downloadable-f721fd3f-6bc4-4549-a197-0a1e907dec32-mcp-conectado.png","isEvidence":false,"id":"report-data-f3ece052-15f2-450a-b34e-badc8bd5cbf0"}],"precondition":false,"level":0},{"number":2,"description":"When se ejecuta la tool verificar_materiales_producto con un id de producto valido y una cantidad a fabricar","duration":0,"startTime":"2026-05-16T23:46:59.540917090-05:00[America/Bogota]","result":"SUCCESS","reportData":[{"title":"Respuesta: materiales suficientes","path":"downloadable/downloadable-c41db8c0-273a-42ab-b5e8-e008c9b5cdb0-tool2-materiales-ok.png","isEvidence":false,"id":"report-data-672d85ce-41fc-4099-bd79-cd31bf649f80"}],"precondition":false,"level":0},{"number":3,"description":"Then el sistema retorna por cada material el nombre, cantidad necesaria, stock actual y cantidad faltante","duration":0,"startTime":"2026-05-16T23:46:59.541794957-05:00[America/Bogota]","result":"SUCCESS","precondition":false,"level":0,"children":[{"number":4,"description":"Verificado: respuesta incluye nombre, cantidadNecesaria, stockActual, cantidadFaltante.","duration":0,"startTime":"2026-05-16T23:46:59.542098638-05:00[America/Bogota]","result":"SUCCESS","precondition":false,"level":1}]},{"number":5,"description":"And el sistema indica que es posible producir la cantidad solicitada","duration":0,"startTime":"2026-05-16T23:46:59.542373249-05:00[America/Bogota]","result":"SUCCESS","precondition":false,"level":0,"children":[{"number":6,"description":"Verificado: puedeProceder \u003d true.","duration":0,"startTime":"2026-05-16T23:46:59.542632326-05:00[America/Bogota]","result":"SUCCESS","precondition":false,"level":1}]}],"userStory":{"id":"mcp-productos","storyName":"HU-19 MCP de gestion de productos","displayName":"HU-19 MCP de gestion de productos","path":"mcp-productos","pathElements":[{"name":"mcp-productos","description":""}],"narrative":"  Como usuario con rol Produccion o Administrador\n  Quiero interactuar con el MCP de productos\n  Para consultar productos, verificar materiales, generar opciones de compra,\n  validar presupuesto y crear ordenes de compra","type":"feature"},"title":"Tool 2 - Verificar materiales con stock suficiente","description":"","tags":[{"name":"IA","type":"tag","displayName":"IA"},{"name":"Linux","type":"context","displayName":"Linux"},{"name":"Chrome","type":"context","displayName":"Chrome"},{"name":"Chrome, Linux","type":"context","displayName":"Chrome, Linux"}],"startTime":"2026-05-16T23:46:59.539355652-05:00[America/Bogota]","endTime":"2026-05-16T23:46:59.545457764-05:00[America/Bogota]","duration":1,"projectKey":"","isManualTestingUpToDate":false,"context":"chrome,linux","manual":false,"testSource":"Cucumber","order":0,"result":"SUCCESS"}