{"name":"Campos obligatorios vacios al editar cliente","id":"hu-11-editar-informacion-de-cliente;campos-obligatorios-vacios-al-editar-cliente","scenarioId":"editar-cliente:Campos obligatorios vacios al editar cliente","methodName":"Campos obligatorios vacios al editar cliente","testSteps":[{"number":1,"description":"Given el usuario ha iniciado sesion en el modulo de clientes","duration":2310,"startTime":"2026-05-17T21:57:22.247890990-05:00[America/Bogota]","screenshots":[{"screenshot":"e5f5826ec4aea85c7831faa5572254ff7f52309a9682e18c1a7838067f192f0b.png","timeStamp":1779073044558,"screenshotName":"e5f5826ec4aea85c7831faa5572254ff7f52309a9682e18c1a7838067f192f0b.png"}],"result":"SUCCESS","precondition":false,"level":0},{"number":2,"description":"Given existe un cliente registrado para la prueba de edicion","duration":1807,"startTime":"2026-05-17T21:57:24.558555936-05:00[America/Bogota]","screenshots":[{"screenshot":"5d80f2e491faf896b298e5fb7b44f700cc811f708b345c9dbd3e2767effa2666.png","timeStamp":1779073046365,"screenshotName":"5d80f2e491faf896b298e5fb7b44f700cc811f708b345c9dbd3e2767effa2666.png"}],"result":"SUCCESS","precondition":false,"level":0},{"number":3,"description":"When el usuario busca y abre el modal de edicion del cliente","duration":378,"startTime":"2026-05-17T21:57:26.366813956-05:00[America/Bogota]","screenshots":[{"screenshot":"6fcea46f29bf8551742f2eb5c8e6ccf4721d090822cea7fee61d795160f3785c.png","timeStamp":1779073046745,"screenshotName":"6fcea46f29bf8551742f2eb5c8e6ccf4721d090822cea7fee61d795160f3785c.png"}],"result":"SUCCESS","precondition":false,"level":0},{"number":4,"description":"And el usuario borra los campos obligatorios del modal de edicion del cliente","duration":24,"startTime":"2026-05-17T21:57:26.746100859-05:00[America/Bogota]","screenshots":[{"screenshot":"6fcea46f29bf8551742f2eb5c8e6ccf4721d090822cea7fee61d795160f3785c.png","timeStamp":1779073046770,"screenshotName":"6fcea46f29bf8551742f2eb5c8e6ccf4721d090822cea7fee61d795160f3785c.png"}],"result":"SUCCESS","precondition":false,"level":0},{"number":5,"description":"And el usuario guarda los cambios del cliente","duration":156,"startTime":"2026-05-17T21:57:26.770559272-05:00[America/Bogota]","screenshots":[{"screenshot":"ce8aadc07d014b73880b4d393f08669a89fb25bc599924bb9d121506c91af6d5.png","timeStamp":1779073046926,"screenshotName":"ce8aadc07d014b73880b4d393f08669a89fb25bc599924bb9d121506c91af6d5.png"}],"result":"SUCCESS","precondition":false,"level":0},{"number":6,"description":"Then el sistema muestra el mensaje de error de edicion de cliente \"Todos los campos obligatorios deben ser diligenciados\"","duration":28,"startTime":"2026-05-17T21:57:26.927353131-05:00[America/Bogota]","screenshots":[{"screenshot":"ce8aadc07d014b73880b4d393f08669a89fb25bc599924bb9d121506c91af6d5.png","timeStamp":1779073046956,"screenshotName":"ce8aadc07d014b73880b4d393f08669a89fb25bc599924bb9d121506c91af6d5.png"}],"result":"SUCCESS","precondition":false,"level":0}],"userStory":{"id":"editar-cliente","storyName":"HU-11 Editar informacion de cliente","displayName":"HU-11 Editar informacion de cliente","path":"editar-cliente","pathElements":[{"name":"editar-cliente","description":""}],"narrative":"  Como usuario con rol Ventas o Administrador\n  Quiero editar la informacion de un cliente\n  Para mantener los datos actualizados y corregir posibles errores","type":"feature"},"title":"Campos obligatorios vacios al editar cliente","description":"","backgroundTitle":"","backgroundDescription":"","tags":[{"name":"clientes","type":"tag","displayName":"clientes"},{"name":"Linux","type":"context","displayName":"Linux"},{"name":"Chrome","type":"context","displayName":"Chrome"},{"name":"Chrome, Linux","type":"context","displayName":"Chrome, Linux"}],"startTime":"2026-05-17T21:57:22.247064811-05:00[America/Bogota]","endTime":"2026-05-17T21:57:26.960546365-05:00[America/Bogota]","duration":1690,"projectKey":"","sessionId":"f549e474adc9f3abba319834769199ca","driver":"chrome","isManualTestingUpToDate":false,"context":"chrome,linux","manual":false,"testSource":"Cucumber","order":0,"result":"SUCCESS"}