{"name":"Registrar gasto operativo","id":"hu-27-registrar-movimiento-de-caja;registrar-gasto-operativo","scenarioId":"registrar-movimiento:Registrar gasto operativo","methodName":"Registrar gasto operativo","testSteps":[{"number":1,"description":"Given el usuario accede al modulo de registrar movimiento de caja","duration":1819,"startTime":"2026-05-18T01:48:56.283229602-05:00[America/Bogota]","screenshots":[{"screenshot":"c82a6b127ce3ff6eb188c5e9b0af1913f6e0516149949c317623f10d3aeb5f01.png","timeStamp":1779086938102,"screenshotName":"c82a6b127ce3ff6eb188c5e9b0af1913f6e0516149949c317623f10d3aeb5f01.png"}],"result":"SUCCESS","precondition":false,"level":0},{"number":2,"description":"When el usuario registra un movimiento de tipo \"Gasto operativo\" con valor 5000","duration":22,"startTime":"2026-05-18T01:48:58.103015009-05:00[America/Bogota]","screenshots":[{"screenshot":"c82a6b127ce3ff6eb188c5e9b0af1913f6e0516149949c317623f10d3aeb5f01.png","timeStamp":1779086938125,"screenshotName":"c82a6b127ce3ff6eb188c5e9b0af1913f6e0516149949c317623f10d3aeb5f01.png"}],"result":"SUCCESS","precondition":false,"level":0},{"number":3,"description":"Then el sistema muestra el mensaje de exito del movimiento \"Movimiento registrado exitosamente\"","duration":255,"startTime":"2026-05-18T01:48:58.125758383-05:00[America/Bogota]","screenshots":[{"screenshot":"5952c41351e90ceb0e7adc7442a00cb1d28ccc5dd6e5c7f3724ab8907c0f1327.png","timeStamp":1779086938381,"screenshotName":"5952c41351e90ceb0e7adc7442a00cb1d28ccc5dd6e5c7f3724ab8907c0f1327.png"}],"result":"SUCCESS","precondition":false,"level":0}],"userStory":{"id":"registrar-movimiento","storyName":"HU-27 Registrar movimiento de caja","displayName":"HU-27 Registrar movimiento de caja","path":"registrar-movimiento","pathElements":[{"name":"registrar-movimiento","description":""}],"narrative":"  Como usuario con rol Tesoreria o Administrador\n  Quiero registrar movimientos manuales en la caja\n  Para reflejar ingresos y egresos no asociados a ventas u ordenes de compra","type":"feature"},"title":"Registrar gasto operativo","description":"","backgroundTitle":"","backgroundDescription":"","tags":[{"name":"Linux","type":"context","displayName":"Linux"},{"name":"caja","type":"tag","displayName":"caja"},{"name":"Chrome","type":"context","displayName":"Chrome"},{"name":"Chrome, Linux","type":"context","displayName":"Chrome, Linux"}],"startTime":"2026-05-18T01:48:56.282113661-05:00[America/Bogota]","endTime":"2026-05-18T01:48:58.385476046-05:00[America/Bogota]","duration":1711,"projectKey":"","sessionId":"0b1f16fe7e12c98fa4158f38337ab5a2","driver":"chrome","isManualTestingUpToDate":false,"context":"chrome,linux","manual":false,"testSource":"Cucumber","order":0,"result":"SUCCESS"}